{
    "posts": [
        {
            "body": "We did an oopsie",
            "image": "1544748225.png",
            "comments": [
                {
                    "comment": "dsf",
                    "commenterUsername": "baswilson"
                },
                {
                    "comment": "Noice",
                    "commenterUsername": "baswilson"
                }
            ],
            "likes": 0,
            "posterUsername": "baswilson"
        },
        {
            "body": "fdsfs",
            "image": 0,
            "comments": [],
            "likes": 4,
            "posterUsername": "baswilson"
        },
        {
            "body": "hfdbsjfbdhjvj",
            "image": "1544772296.jpg",
            "comments": [
                {
                    "comment": "lit",
                    "commenterUsername": "baswilson"
                },
                {
                    "comment": "sexy pick",
                    "commenterUsername": "aye12"
                }
            ],
            "likes": 2,
            "posterUsername": "baswilson"
        },
        {
            "body": "Test",
            "image": 0,
            "comments": [],
            "likes": 1,
            "posterUsername": "aye"
        },
        {
            "body": "ayeeee",
            "image": 0,
            "comments": [
                {
                    "comment": "Hoi boi",
                    "commenterUsername": "aye12"
                },
                {
                    "comment": "fbhsdjfds",
                    "commenterUsername": "aye12"
                }
            ],
            "likes": 1,
            "posterUsername": "aye"
        },
        {
            "body": "Is this the next tumbler",
            "image": "1544786150.jpg",
            "comments": [
                {
                    "comment": "fdsfsdf",
                    "commenterUsername": "aye12"
                }
            ],
            "likes": 0,
            "posterUsername": "aye12"
        }
    ]
}